{
    "python.condaPath": "/home/julian/miniconda3/condabin/conda",
    "python.venvPath": "/home/julian/miniconda3/envs",
    "rust-analyzer.serverPath": "/home/julian/.cargo/bin/rust-analyzer",
    "python.jediEnabled": false,
    "tsserver.npm": "/usr/local/bin/npm",
    "languageserver": {
        "ccls": {
            "command": "ccls",
            "filetypes": ["c", "cc", "cpp", "c++", "objc", "objcpp"],
            "rootPatterns": [".ccls", "compile_commands.json", ".git/", ".hg/"],
            "initializationOptions": {
                "cache": {
                    "directory": "/tmp/ccls"
                }
           }
        }
    },
    "coc.preferences.jumpCommand": "tab drop",
    "diagnostic.refreshOnInsertMode": true,
    "coc.preferences.rootPatterns":  [".vim",".git",".hg",".projections.json, Cargo.toml"]
}
